[
    {
        "id":1,
        "year":1,
        "semester":1,
        "subject_code": "CO 1",
        "lec_hours":1,
        "lab_hours":0,
        "units":1
    },
    {
        "id":2,
        "year":1,
        "semester":1,
        "subject_code": "UTS 1",
        "lec_hours":3,
        "lab_hours":0,
        "units":3
    },
    {
        "id":3,
        "year":1,
        "semester":1,
        "subject_code": "History 1",
        "lec_hours":3,
        "lab_hours":0,
        "units":3
    },
    {
        "id":4,
        "year":1,
        "semester":1,
        "subject_code": "Eng 1",
        "lec_hours":3,
        "lab_hours":0,
        "units":3
    },
    {
        "id":5,
        "year":1,
        "semester":1,
        "subject_code": "Math 1",
        "lec_hours":3,
        "lab_hours":0,
        "units":3
    },
    {
        "id":6,
        "year":1,
        "semester":1,
        "subject_code": "CC 101",
        "lec_hours":2,
        "lab_hours":3,
        "units":3
    },
    {
        "id":7,
        "year":1,
        "semester":1,
        "subject_code": "CC 102",
        "lec_hours":2,
        "lab_hours":3,
        "units":3
    },
    {
        "id":8,
        "year":1,
        "semester":1,
        "subject_code": "PE 1",
        "lec_hours":2,
        "lab_hours":0,
        "units":3
    },
    {
        "id":9,
        "year":1,
        "semester":1,
        "subject_code": "NTSP 1",
        "lec_hours":3,
        "lab_hours":0,
        "units":3
    },

    {
        "id":10,
        "year":1,
        "semester":2,
        "subject_code": "CW 1",
        "lec_hours":3,
        "lab_hours":0,
        "units":3
    },
    {
        "id":11,
        "year":1,
        "semester":2,
        "subject_code": "Hum 1",
        "lec_hours":3,
        "lab_hours":0,
        "units":3
    },
    {
        "id":12,
        "year":1,
        "semester":2,
        "subject_code": "STS 1",
        "lec_hours":3,
        "lab_hours":0,
        "units":3
    },
    {
        "id":13,
        "year":1,
        "semester":2,
        "subject_code": "Hum 2",
        "lec_hours":3,
        "lab_hours":0,
        "units":3
    },
    {
        "id":14,
        "year":1,
        "semester":2,
        "subject_code": "CC 103",
        "lec_hours":2,
        "lab_hours":3,
        "units":3
    },
    {
        "id":15,
        "year":1,
        "semester":2,
        "subject_code": "CC 104",
        "lec_hours":2,
        "lab_hours":3,
        "units":3
    },
    {
        "id":16,
        "year":1,
        "semester":2,
        "subject_code": "PE 2",
        "lec_hours":2,
        "lab_hours":0,
        "units":2
    },
    {
        "id":17,
        "year":1,
        "semester":2,
        "subject_code": "NTSP 2",
        "lec_hours":3,
        "lab_hours":0,
        "units":3
    },
    

    {
        "id":18,
        "year":2,
        "semester":1,
        "subject_code": "Fil 1",
        "lec_hours":3,
        "lab_hours":0,
        "units":3
    },
    {
        "id":19,
        "year":2,
        "semester":1,
        "subject_code": "Ethics 1",
        "lec_hours":3,
        "lab_hours":0,
        "units":3
    },
    {
        "id":20,
        "year":2,
        "semester":1,
        "subject_code": "STS 2",
        "lec_hours":3,
        "lab_hours":0,
        "units":3
    },
    {
        "id":21,
        "year":2,
        "semester":1,
        "subject_code": "CC 104",
        "lec_hours":2,
        "lab_hours":3,
        "units":3
    },
    {
        "id":22,
        "year":2,
        "semester":1,
        "subject_code": "CC 105",
        "lec_hours":2,
        "lab_hours":3,
        "units":3
    },
    {
        "id":23,
        "year":2,
        "semester":1,
        "subject_code": "IT 1",
        "lec_hours":3,
        "lab_hours":0,
        "units":3
    },
    {
        "id":24,
        "year":2,
        "semester":1,
        "subject_code": "IT 2",
        "lec_hours":3,
        "lab_hours":0,
        "units":3
    },
    {
        "id":25,
        "year":2,
        "semester":1,
        "subject_code": "IT 3",
        "lec_hours":3,
        "lab_hours":0,
        "units":3
    },
    {
        "id":26,
        "year":2,
        "semester":1,
        "subject_code": "PE 3",
        "lec_hours":2,
        "lab_hours":0,
        "units":2
    },

    {
        "id":27,
        "year":2,
        "semester":2,
        "subject_code": "Fil 2",
        "lec_hours":3,
        "lab_hours":0,
        "units":3
    },
    {
        "id":10,
        "year":2,
        "semester":2,
        "subject_code": "Ethics 1",
        "lec_hours":3,
        "lab_hours":0,
        "units":3
    },
    {
        "id":28,
        "year":2,
        "semester":2,
        "subject_code": "STS 2",
        "lec_hours":3,
        "lab_hours":0,
        "units":3
    },
    {
        "id":29,
        "year":2,
        "semester":2,
        "subject_code": "CC 104",
        "lec_hours":2,
        "lab_hours":3,
        "units":3
    },
    {
        "id":30,
        "year":2,
        "semester":2,
        "subject_code": "CC 105",
        "lec_hours":2,
        "lab_hours":3,
        "units":3
    },
    {
        "id":31,
        "year":2,
        "semester":2,
        "subject_code": "IT 4",
        "lec_hours":2,
        "lab_hours":3,
        "units":3
    },
    {
        "id":32,
        "year":2,
        "semester":2,
        "subject_code": "IT 5",
        "lec_hours":3,
        "lab_hours":0,
        "units":3
    },
    {
        "id":33,
        "year":2,
        "semester":2,
        "subject_code": "IT 6",
        "lec_hours":2,
        "lab_hours":3,
        "units":3
    },
    {
        "id":34,
        "year":2,
        "semester":2,
        "subject_code": "IT 7",
        "lec_hours":3,
        "lab_hours":0,
        "units":3
    },

    {
        "id":35,
        "year":2,
        "semester":2,
        "subject_code": "IT 8",
        "lec_hours":2,
        "lab_hours":3,
        "units":3
    },
    {
        "id":36,
        "year":2,
        "semester":2,
        "subject_code": "PE 4",
        "lec_hours":2,
        "lab_hours":0,
        "units":2
    }
]